llama_jarvis/__about__.py
llama_jarvis/__init__.py
llama_jarvis/base.py
llama_jarvis/model.py
llama_jarvis/utils.py
llama_jarvis-0.1.0.dist-info/METADATA
llama_jarvis-0.1.0.dist-info/WHEEL
llama_jarvis-0.1.0.dist-info/licenses/LICENSE.txt
llama_jarvis-0.1.0.dist-info/RECORD
