Metadata-Version: 2.3
Name: llama-jarvis
Version: 0.1.0
Summary: Train a speech-to-speech model using your own language model
Project-URL: Documentation, https://github.com/johnsutor/llama-jarvis#readme
Project-URL: Issues, https://github.com/johnsutor/llama-jarvis/issues
Project-URL: Source, https://github.com/johnsutor/llama-jarvis
Author-email: John Sutor <johnsutor3@gmail.com>
License-Expression: MIT
License-File: LICENSE.txt
Keywords: llama,llm,speech-to-speech,transformers
Classifier: Development Status :: 4 - Beta
Classifier: License :: OSI Approved :: MIT License
Classifier: Operating System :: OS Independent
Classifier: Programming Language :: Python
Classifier: Programming Language :: Python :: 3
Classifier: Programming Language :: Python :: 3.8
Classifier: Programming Language :: Python :: 3.9
Classifier: Programming Language :: Python :: 3.10
Classifier: Programming Language :: Python :: 3.11
Classifier: Programming Language :: Python :: 3.12
Classifier: Programming Language :: Python :: Implementation :: CPython
Classifier: Programming Language :: Python :: Implementation :: PyPy
Requires-Python: >=3.8
Requires-Dist: torch
Requires-Dist: transformers
Provides-Extra: dev
Requires-Dist: hatch; extra == 'dev'
Requires-Dist: mypy; extra == 'dev'
Requires-Dist: pytest; extra == 'dev'
Requires-Dist: pytest-cov; extra == 'dev'
Requires-Dist: ruff; extra == 'dev'
